uiprotect/__init__.py
uiprotect/__main__.py
uiprotect/_compat.py
uiprotect/api.py
uiprotect/cli/__init__.py
uiprotect/cli/aiports.py
uiprotect/cli/backup.py
uiprotect/cli/base.py
uiprotect/cli/cameras.py
uiprotect/cli/chimes.py
uiprotect/cli/doorlocks.py
uiprotect/cli/events.py
uiprotect/cli/lights.py
uiprotect/cli/liveviews.py
uiprotect/cli/nvr.py
uiprotect/cli/sensors.py
uiprotect/cli/viewers.py
uiprotect/data/__init__.py
uiprotect/data/base.py
uiprotect/data/bootstrap.py
uiprotect/data/convert.py
uiprotect/data/devices.py
uiprotect/data/nvr.py
uiprotect/data/types.py
uiprotect/data/user.py
uiprotect/data/websocket.py
uiprotect/exceptions.py
uiprotect/py.typed
uiprotect/release_cache.json
uiprotect/stream.py
uiprotect/test_util/__init__.py
uiprotect/test_util/anonymize.py
uiprotect/utils.py
uiprotect/websocket.py
uiprotect-10.1.0.dist-info/METADATA
uiprotect-10.1.0.dist-info/WHEEL
uiprotect-10.1.0.dist-info/entry_points.txt
uiprotect-10.1.0.dist-info/licenses/LICENSE
uiprotect-10.1.0.dist-info/RECORD
