Metadata-Version: 2.4
Name: uiprotect
Version: 10.1.0
Summary: Python API for Unifi Protect (Unofficial)
License-Expression: MIT
License-File: LICENSE
Author: UI Protect Maintainers
Author-email: ui@koston.org
Requires-Python: >=3.11
Classifier: Development Status :: 5 - Production/Stable
Classifier: Intended Audience :: Developers
Classifier: Natural Language :: English
Classifier: Operating System :: OS Independent
Classifier: Programming Language :: Python :: 3
Classifier: Programming Language :: Python :: 3.11
Classifier: Programming Language :: Python :: 3.12
Classifier: Programming Language :: Python :: 3.13
Classifier: Programming Language :: Python :: 3.14
Classifier: Topic :: Software Development :: Build Tools
Classifier: Topic :: Software Development :: Libraries
Requires-Dist: aiofiles (>=24)
Requires-Dist: aiohttp (>=3.10.0)
Requires-Dist: aioshutil (>=1.3)
Requires-Dist: async-timeout (>=3.0.1)
Requires-Dist: av (>=16)
Requires-Dist: convertertools (>=0.5.0)
Requires-Dist: dateparser (>=1.1.0)
Requires-Dist: orjson (>=3.9.15)
Requires-Dist: packaging (>=23)
Requires-Dist: pillow (>=10)
Requires-Dist: platformdirs (>=4)
Requires-Dist: propcache (>=0.0.0)
Requires-Dist: pydantic (>=2.10.0)
Requires-Dist: pydantic-extra-types (>=2.10.1)
Requires-Dist: pyjwt (>=2.6)
Requires-Dist: rich (>=10)
Requires-Dist: typer (>=0.12.3)
Requires-Dist: yarl (>=1.9)
Project-URL: Bug Tracker, https://github.com/uilibs/uiprotect/issues
Project-URL: Changelog, https://github.com/uilibs/uiprotect/blob/main/CHANGELOG.md
Project-URL: Documentation, https://uiprotect.readthedocs.io
Project-URL: Repository, https://github.com/uilibs/uiprotect
